<annotation><filename>person310180.jpg</filename><folder>users/aitormf//person</folder><source><submittedBy>Aitor</submittedBy></source><imagesize><nrows>100</nrows><ncols>150</ncols></imagesize><object><name>person</name><deleted>0</deleted><verified>0</verified><occluded>no</occluded><attributes></attributes><parts><hasparts></hasparts><ispartof></ispartof></parts><date>17-06-20 18:49:03:335</date><id>0</id><type>bounding_box</type><polygon><username>anonymous</username><pt><x>71</x><y>42</y><time>17-06-20 18:49:00:360</time></pt><pt><x>76</x><y>42</y><time>17-06-20 18:49:01:614</time></pt><pt><x>76</x><y>55</y><time>undefined</time></pt><pt><x>71</x><y>55</y><time>undefined</time></pt><closed_date>17-06-20 18:49:01:614</closed_date></polygon></object></annotation>