<annotation><filename>person0235335.jpg</filename><folder>users/aitormf//person</folder><source><submittedBy>Aitor</submittedBy></source><imagesize><nrows>100</nrows><ncols>150</ncols></imagesize><object><name>person</name><deleted>0</deleted><verified>0</verified><occluded>no</occluded><attributes /><parts><hasparts /><ispartof /></parts><date>15-06-20 19:26:30:359</date><id>0</id><type>bounding_box</type><polygon><username>anonymous</username><closed_date>15-06-20 19:26:25:792</closed_date><pt><x>70</x><y>41</y><time>15-06-20 19:26:25:791</time></pt><pt><x>81</x><y>41</y><time>15-06-20 19:26:23:767</time></pt><pt><x>81</x><y>63</y><time>undefined</time></pt><pt><x>70</x><y>63</y><time>undefined</time></pt></polygon></object></annotation>