<annotation><filename>person02210174.jpg</filename><folder>users/aitormf//person</folder><source><submittedBy>Aitor</submittedBy></source><imagesize><nrows>100</nrows><ncols>150</ncols></imagesize><object><name>person</name><deleted>0</deleted><verified>0</verified><occluded>no</occluded><attributes /><parts><hasparts /><ispartof /></parts><date>16-06-20 14:17:27:389</date><id>0</id><type>bounding_box</type><polygon><username>anonymous</username><closed_date>16-06-20 14:17:25:480</closed_date><pt><x>72</x><y>46</y><time>16-06-20 14:17:25:480</time></pt><pt><x>81</x><y>46</y><time>16-06-20 14:17:24:535</time></pt><pt><x>81</x><y>55</y><time>undefined</time></pt><pt><x>72</x><y>55</y><time>undefined</time></pt></polygon></object></annotation>