<annotation><filename>person02315150.jpg</filename><folder>users/aitormf//person</folder><source><submittedBy>Aitor</submittedBy></source><imagesize><nrows>100</nrows><ncols>150</ncols></imagesize><object><name>person</name><deleted>0</deleted><verified>0</verified><occluded>no</occluded><attributes /><parts><hasparts /><ispartof /></parts><date>15-06-20 19:10:52:948</date><id>0</id><type>bounding_box</type><polygon><username>anonymous</username><closed_date>15-06-20 19:10:48:756</closed_date><pt><x>74</x><y>49</y><time>15-06-20 19:10:48:755</time></pt><pt><x>78</x><y>49</y><time>15-06-20 19:10:47:192</time></pt><pt><x>78</x><y>54</y><time>undefined</time></pt><pt><x>74</x><y>54</y><time>undefined</time></pt></polygon></object><object><name>road</name><deleted>0</deleted><verified>0</verified><occluded>no</occluded><attributes /><parts><hasparts /><ispartof /></parts><date>15-06-20 19:11:13:276</date><id>1</id><type>bounding_box</type><polygon><username>anonymous</username><closed_date>15-06-20 19:11:08:183</closed_date><pt><x>134</x><y>73</y><time>15-06-20 19:11:08:183</time></pt><pt><x>1</x><y>73</y><time>15-06-20 19:11:03:597</time></pt><pt><x>1</x><y>100</y><time>undefined</time></pt><pt><x>134</x><y>100</y><time>undefined</time></pt></polygon></object></annotation>