<annotation><filename>person0215341.jpg</filename><folder>users/aitormf//person</folder><source><submittedBy>Aitor</submittedBy></source><imagesize><nrows>100</nrows><ncols>150</ncols></imagesize><object><name>person</name><deleted>0</deleted><verified>0</verified><occluded>no</occluded><attributes /><parts><hasparts /><ispartof /></parts><date>16-06-20 11:18:11:622</date><id>0</id><type>bounding_box</type><polygon><username>anonymous</username><closed_date>16-06-20 11:18:08:483</closed_date><pt><x>57</x><y>47</y><time>16-06-20 11:18:08:483</time></pt><pt><x>90</x><y>47</y><time>16-06-20 11:18:05:253</time></pt><pt><x>90</x><y>20</y><time>undefined</time></pt><pt><x>57</x><y>20</y><time>undefined</time></pt></polygon></object></annotation>